README
setup.py
bin/lexicographer
bin/make_dictionary
bin/summon
golem/__init__.py
golem.egg-info/PKG-INFO
golem.egg-info/SOURCES.txt
golem.egg-info/dependency_links.txt
golem.egg-info/requires.txt
golem.egg-info/top_level.txt
golem/db/__init__.py
golem/db/berkeley.py
golem/db/conceptlist.py
golem/db/fs.py
golem/db/resultlist.py
golem/helpers/__init__.py
golem/helpers/dataset.py
golem/helpers/dict.py
golem/helpers/function.py
golem/helpers/generics.py
golem/helpers/output.py
golem/helpers/stream.py
golem/helpers/xpath.py