Metadata-Version: 1.0
Name: golem
Version: 1.01
Summary: Ontology language and toolkit for semantic processing of scientific data
Home-page: http://www.lexical.org.uk/science/golem/
Author: Andrew Walkingshaw
Author-email: andrew@lexical.org.uk
License: MIT
Download-URL: http://code.google.com/p/pygolem/downloads
Platform: UNKNOWN
